src/ALU.v
module ALU(
    input [63:0]X,
    input [63:0]Y,
    input [3:0]OP,

    output reg [63:0]result_reg,
    output isEqual
);
    wire signed [63:0] X_signed = X;
    wire signed [63:0] Y_signed = Y;

    assign isEqual = X == Y;

    always @(*) begin
        case (OP)
            0:  result_reg <= X + Y; // add
            1:  result_reg <= X - Y; // sub
            2:  result_reg <= X & Y; // and
            3:  result_reg <= X | Y; // or
            4:  result_reg <= X ^ Y; // xor
            5:  result_reg <= X << Y; // shift left logical
            6:  result_reg <= X >> Y; // shift right logical
            7:  result_reg <= X_signed >>> Y; // shift right arithmetic
            8:  result_reg <= X * Y; // mul
            9:  result_reg <= X * Y; // mulh will be implemented
            10: result_reg <= X / Y; // div
            11: result_reg <= X % Y; // rem
            12: result_reg <= (X_signed < Y_signed ? 1 : 0); // set less than (slt)
            13: result_reg <= (X < Y ? 1 : 0); // set less than (sltu)
        endcase
    end

    

endmodule

testbench/tb_ALU.v
`include "ALU.v"
`timescale 1ns / 100ps 

module tb_ALU;
    reg [63:0]a;
    reg [63:0]b;
    reg [3:0]op;

    wire [63:0]result;
    wire isEqual;

    ALU alu(a, b, op, result, isEqual );

    initial begin
        // ADD
        a = 5;
        b = 5;
        op = 0;
        #20;

        // SUB
        a = 66;
        b = 11;
        op = 1;
        #20;

        // AND
        a = 3'b101;
        b = 3'b110;
        op = 2;
        #20;

        // OR
        a = 3'b101;
        b = 3'b110;
        op = 3;
        #20;

        // XOR
        a = 3'b110;
        b = 3'b010;
        op = 4;
        #20;

        // Shift Left Logical
        a = 1;
        b = 3;
        op = 5;
        #20;

        // Shift Right Logical
        a = 8;
        b = 2;
        op = 6;
        #20;

        // Shift Right Arithmetic
        a = -8;
        b = 2;
        op = 7;
        #20;

        // Multiply
        a = 6;
        b = 5;
        op = 8;
        #20;

        // Multiply High
        a = 5;
        b = 3;
        op = 9;
        #20;

        // Divide
        a = 66;
        b = 11;
        op = 10;
        #20;

        // Remainder
        a = 62;
        b = 3;
        op = 11;
        #20;

        // Signed Less Than
        a = -1;
        b = 9;
        op = 12;
        #20;

        // Unsigned Less Than
        a = -1;
        b = 9;
        op = 13;
        #20;
    end

    initial begin
        $dumpfile("vcd/alu.vcd");
        $dumpvars(0, tb_ALU);
    end
endmodule

testbench/vcd/alu.vcd
$date
	Mon May 24 15:33:45 2021
$end
$version
	Icarus Verilog
$end
$timescale
	100ps
$end
$scope module tb_ALU $end
$var wire 64 ! result [63:0] $end
$var wire 1 " isEqual $end
$var reg 64 # a [63:0] $end
$var reg 64 $ b [63:0] $end
$var reg 4 % op [3:0] $end
$scope module alu $end
$var wire 4 & OP [3:0] $end
$var wire 64 ' X [63:0] $end
$var wire 64 ( X_signed [63:0] $end
$var wire 64 ) Y [63:0] $end
$var wire 64 * Y_signed [63:0] $end
$var wire 1 " isEqual $end
$var reg 64 + result_reg [63:0] $end
$upscope $end
$upscope $end
$enddefinitions $end
#0
$dumpvars
b1010 +
b101 *
b101 )
b101 (
b101 '
b0 &
b0 %
b101 $
b101 #
1"
b1010 !
$end
#200
b110111 !
b110111 +
b1 %
b1 &
b1011 *
b1011 $
b1011 )
b1000010 (
0"
b1000010 #
b1000010 '
#400
b100 !
b100 +
b10 %
b10 &
b110 *
b110 $
b110 )
b101 (
b101 #
b101 '
#600
b111 !
b111 +
b11 %
b11 &
#800
b100 !
b100 +
b100 %
b100 &
b10 *
b10 $
b10 )
b110 (
0"
b110 #
b110 '
#1000
b1000 !
b1000 +
b101 %
b101 &
b11 *
b11 $
b11 )
b1 (
b1 #
b1 '
#1200
b10 !
b10 +
b110 %
b110 &
b10 *
b10 $
b10 )
b1000 (
b1000 #
b1000 '
#1400
b1111111111111111111111111111111111111111111111111111111111111110 !
b1111111111111111111111111111111111111111111111111111111111111110 +
b111 %
b111 &
b1111111111111111111111111111111111111111111111111111111111111000 (
b1111111111111111111111111111111111111111111111111111111111111000 #
b1111111111111111111111111111111111111111111111111111111111111000 '
#1600
b11110 !
b11110 +
b1000 %
b1000 &
b101 *
b101 $
b101 )
b110 (
b110 #
b110 '
#1800
b1111 !
b1111 +
b1001 %
b1001 &
b11 *
b11 $
b11 )
b101 (
0"
b101 #
b101 '
#2000
b110 !
b110 +
b1010 %
b1010 &
b1011 *
b1011 $
b1011 )
b1000010 (
b1000010 #
b1000010 '
#2200
b10 !
b10 +
b1011 %
b1011 &
b11 *
b11 $
b11 )
b111110 (
b111110 #
b111110 '
#2400
b1 !
b1 +
b1100 %
b1100 &
b1001 *
b1001 $
b1001 )
b1111111111111111111111111111111111111111111111111111111111111111 (
b1111111111111111111111111111111111111111111111111111111111111111 #
b1111111111111111111111111111111111111111111111111111111111111111 '
#2600
b0 !
b0 +
b1101 %
b1101 &
