src/ALU.v
module ALU(
    input [63:0] X,
    input [63:0] Y,
    input [3:0] OP,

    output [63:0] OUTPUT,
    output isEqual
);
    reg [63:0] RESULT;
    reg [127:0] RESULT_MULH;

    wire signed [63:0] X_signed = X;
    wire signed [63:0] Y_signed = Y;

    assign isEqual = X == Y;

    always @(*) begin
        case (OP)
            0:  RESULT <= X + Y; // add
            1:  RESULT <= X - Y; // sub
            2:  RESULT <= X & Y; // and
            3:  RESULT <= X | Y; // or
            4:  RESULT <= X ^ Y; // xor
            5:  RESULT <= X << Y; // shift left logical
            6:  RESULT <= X >> Y; // shift right logical
            7:  RESULT <= X_signed >>> Y; // shift right arithmetic
            8:  RESULT <= X * Y; // mul
            9:  RESULT_MULH <= X * Y; // mulh
            10: RESULT <= X / Y; // div
            11: RESULT <= X % Y; // rem
            12: RESULT <= (X_signed < Y_signed ? 1 : 0); // set less than (slt)
            13: RESULT <= (X < Y ? 1 : 0); // set less than (sltu)
        endcase
    end

    assign OUTPUT = OP == 9 ? RESULT_MULH[127:64] : RESULT;

endmodule

testbench/tb_ALU.v
`include "ALU.v"
`timescale 1ns / 100ps 

module tb_ALU;
    reg [63:0] a;
    reg [63:0] b;
    reg [3:0]  op;

    wire [63:0] result;
    wire isEqual;

    ALU alu(a, b, op, result, isEqual);

    initial begin
        // add
        a = 5;          b = 5;      op = 0; #20;
        // sub
        a = 66;         b = 11;     op = 1; #20;        
        // and
        a = 3'b101;     b = 3'b110; op = 2; #20;
        // or
        a = 3'b101;     b = 3'b110; op = 3; #20;
        // xor
        a = 3'b110;     b = 3'b010; op = 4; #20;
        // sll (Shift Left Logical)
        a = 1;          b = 3;      op = 5; #20;
        // srl (Shift Right Logical)
        a = 8;          b = 2;      op = 6; #20;
        // sra (Shift Right Arithmetic)
        a = -8;         b = 2;      op = 7; #20;
        // mul
        a = 6;          b = 5;      op = 8; #20;
        // mulh
        a = 64'h8000000000000000;   b = 4;  op = 9; #20; // output will be ...0010 = 2
        // div
        a = 66;         b = 11;     op = 10; #20;
        // rem
        a = 62;         b = 3;      op = 11; #20;
        // slt (Set Less Than)
        a = -1;         b = 9;      op = 12; #20;
        // sltu (Set Less Than Unsigned)
        a = -1;         b = 9;      op = 13; #20;
    end

    initial begin
        $dumpfile("vcd/alu.vcd");
        $dumpvars(0, tb_ALU);
    end
endmodule

testbench/vcd/alu.vcd
$date
	Tue May 25 21:18:16 2021
$end
$version
	Icarus Verilog
$end
$timescale
	100ps
$end
$scope module tb_ALU $end
$var wire 64 ! result [63:0] $end
$var wire 1 " isEqual $end
$var reg 64 # a [63:0] $end
$var reg 64 $ b [63:0] $end
$var reg 4 % op [3:0] $end
$scope module alu $end
$var wire 4 & OP [3:0] $end
$var wire 64 ' X [63:0] $end
$var wire 64 ( X_signed [63:0] $end
$var wire 64 ) Y [63:0] $end
$var wire 64 * Y_signed [63:0] $end
$var wire 1 " isEqual $end
$var wire 64 + OUTPUT [63:0] $end
$var reg 64 , RESULT [63:0] $end
$var reg 128 - RESULT_MULH [127:0] $end
$upscope $end
$upscope $end
$enddefinitions $end
#0
$dumpvars
bx -
b1010 ,
b1010 +
b101 *
b101 )
b101 (
b101 '
b0 &
b0 %
b101 $
b101 #
1"
b1010 !
$end
#200
b110111 !
b110111 +
b110111 ,
b1 %
b1 &
b1011 *
b1011 $
b1011 )
b1000010 (
0"
b1000010 #
b1000010 '
#400
b100 !
b100 +
b100 ,
b10 %
b10 &
b110 *
b110 $
b110 )
b101 (
b101 #
b101 '
#600
b111 !
b111 +
b111 ,
b11 %
b11 &
#800
b100 !
b100 +
b100 ,
b100 %
b100 &
b10 *
b10 $
b10 )
b110 (
0"
b110 #
b110 '
#1000
b1000 !
b1000 +
b1000 ,
b101 %
b101 &
b11 *
b11 $
b11 )
b1 (
b1 #
b1 '
#1200
b10 !
b10 +
b10 ,
b110 %
b110 &
b10 *
b10 $
b10 )
b1000 (
b1000 #
b1000 '
#1400
b1111111111111111111111111111111111111111111111111111111111111110 !
b1111111111111111111111111111111111111111111111111111111111111110 +
b1111111111111111111111111111111111111111111111111111111111111110 ,
b111 %
b111 &
b1111111111111111111111111111111111111111111111111111111111111000 (
b1111111111111111111111111111111111111111111111111111111111111000 #
b1111111111111111111111111111111111111111111111111111111111111000 '
#1600
b11110 !
b11110 +
b11110 ,
b1000 %
b1000 &
b101 *
b101 $
b101 )
b110 (
b110 #
b110 '
#1800
b100000000000000000000000000000000000000000000000000000000000000000 -
b10 !
b10 +
b1001 %
b1001 &
b100 *
b100 $
b100 )
b1000000000000000000000000000000000000000000000000000000000000000 (
b1000000000000000000000000000000000000000000000000000000000000000 #
b1000000000000000000000000000000000000000000000000000000000000000 '
#2000
b110 ,
b110 !
b110 +
b1010 %
b1010 &
b1011 *
b1011 $
b1011 )
b1000010 (
b1000010 #
b1000010 '
#2200
b10 !
b10 +
b10 ,
b1011 %
b1011 &
b11 *
b11 $
b11 )
b111110 (
b111110 #
b111110 '
#2400
b1 !
b1 +
b1 ,
b1100 %
b1100 &
b1001 *
b1001 $
b1001 )
b1111111111111111111111111111111111111111111111111111111111111111 (
b1111111111111111111111111111111111111111111111111111111111111111 #
b1111111111111111111111111111111111111111111111111111111111111111 '
#2600
b0 !
b0 +
b0 ,
b1101 %
b1101 &
