src/Encoders.v
module Encoder_4 (
    input [3:0] in,
    output reg [1:0] out
  );
  initial begin
    out = 0;
  end

  always @(in) begin
    casex (in)
      4'b1xxx : out = 3;
      4'b01xx : out = 2;
      4'b001x : out = 1;
      4'b0001 : out = 0;
      4'b0000 : out = 0;
      default: out = 0;
    endcase
  end
endmodule

module Encoder_8 (
    input [7:0] in,
    output reg [2:0] out
  );
  initial begin
    out = 0;
  end
  
  always @(in) begin
    casex (in)
      8'b1xxxxxxx : out = 7;
      8'b01xxxxxx : out = 6;
      8'b001xxxxx : out = 5;
      8'b0001xxxx : out = 4;
      8'b00001xxx : out = 3;
      8'b000001xx : out = 2;
      8'b0000001x : out = 1;
      8'b00000001 : out = 0;
      8'b00000000 : out = 0;
      default: out = 0;
    endcase
  end
  
endmodule

module Encoder_16 (
    input [15:0] in,
    output reg [3:0] out
  );
  initial begin
    out = 0;
  end
  
  always @(in) begin
    casex (in)
      16'b1xxxxxxxxxxxxxxx : out = 15;
      16'b01xxxxxxxxxxxxxx : out = 14;
      16'b001xxxxxxxxxxxxx : out = 13;
      16'b0001xxxxxxxxxxxx : out = 12;
      16'b00001xxxxxxxxxxx : out = 11;
      16'b000001xxxxxxxxxx : out = 10;
      16'b0000001xxxxxxxxx : out = 9;
      16'b00000001xxxxxxxx : out = 8;
      16'b000000001xxxxxxx : out = 7;
      16'b0000000001xxxxxx : out = 6;
      16'b00000000001xxxxx : out = 5;
      16'b000000000001xxxx : out = 4;
      16'b0000000000001xxx : out = 3;
      16'b00000000000001xx : out = 2;
      16'b000000000000001x : out = 1;
      16'b0000000000000001 : out = 0;
      16'b0000000000000000 : out = 0;
      default: out = 0;
    endcase
  end
  
endmodule

testbench/tb_Encoder.v
`include "Encoders.v"

`timescale 1ns / 100ps 

module tb_Encoder;
    reg [15:0] in = 0;
    reg enable = 1;
    reg [3:0] out4;
    reg [2:0] out3;
    reg [1:0] out2;
    reg hasValue;

    Encoder_16 enc(in, out4);
    Encoder_8 enc8(in[7:0], out3);
    Encoder_4 enc4(in[3:0], out2);

    initial begin
        in = 16'b0000000000000000; #20;
        in = 16'b0000000000000001; #20;
        in = 16'b0000000000000010; #20;
        in = 16'b0000000000000100; #20;
        in = 16'b0000000000001000; #20;
        in = 16'b0000000000010000; #20;
        in = 16'b0000000000100000; #20;
        in = 16'b0000000001000000; #20;
        in = 16'b0000000010000000; #20;
        in = 16'b0000000100000000; #20;
        in = 16'b0000001000000000; #20;
        in = 16'b0000010000000000; #20;
        in = 16'b0000100000000000; #20;
        in = 16'b0001000000000000; #20;
        in = 16'b0010000000000000; #20;
        in = 16'b0100000000000000; #20;
        in = 16'b1000000000000000; #20;
        in = 16'b1000000000000001; #20;
        in = 16'b0000000100000001; #20;
        in = 16'b0000000000000011; #20;
        in = 16'b0000000000000000; #20;
        
    end

    initial begin
        $dumpfile("vcd/encoder.vcd");
        $dumpvars(0, tb_Encoder);
    end

endmodule

testbench/vcd/encoder.vcd
$date
	Fri May 21 16:40:12 2021
$end
$version
	Icarus Verilog
$end
$timescale
	100ps
$end
$scope module tb_Encoder $end
$var wire 4 ! out4 [3:0] $end
$var wire 3 " out3 [2:0] $end
$var wire 2 # out2 [1:0] $end
$var reg 1 $ enable $end
$var reg 16 % in [15:0] $end
$scope module enc $end
$var wire 16 & in [15:0] $end
$var reg 4 ' out [3:0] $end
$upscope $end
$scope module enc4 $end
$var wire 4 ( in [3:0] $end
$var reg 2 ) out [1:0] $end
$upscope $end
$scope module enc8 $end
$var wire 8 * in [7:0] $end
$var reg 3 + out [2:0] $end
$upscope $end
$upscope $end
$enddefinitions $end
#0
$dumpvars
b0 +
b0 *
b0 )
b0 (
b0 '
b0 &
b0 %
1$
b0 #
b0 "
b0 !
$end
#200
b1 *
b1 (
b1 %
b1 &
#400
b1 "
b1 +
b1 #
b1 )
b10 *
b10 (
b1 !
b1 '
b10 %
b10 &
#600
b10 "
b10 +
b10 #
b10 )
b100 *
b100 (
b10 !
b10 '
b100 %
b100 &
#800
b11 "
b11 +
b11 #
b11 )
b1000 *
b1000 (
b11 !
b11 '
b1000 %
b1000 &
#1000
b100 "
b100 +
b0 #
b0 )
b10000 *
b0 (
b100 !
b100 '
b10000 %
b10000 &
#1200
b101 "
b101 +
b100000 *
b101 !
b101 '
b100000 %
b100000 &
#1400
b110 "
b110 +
b1000000 *
b110 !
b110 '
b1000000 %
b1000000 &
#1600
b111 "
b111 +
b10000000 *
b111 !
b111 '
b10000000 %
b10000000 &
#1800
b0 "
b0 +
b0 *
b1000 !
b1000 '
b100000000 %
b100000000 &
#2000
b1001 !
b1001 '
b1000000000 %
b1000000000 &
#2200
b1010 !
b1010 '
b10000000000 %
b10000000000 &
#2400
b1011 !
b1011 '
b100000000000 %
b100000000000 &
#2600
b1100 !
b1100 '
b1000000000000 %
b1000000000000 &
#2800
b1101 !
b1101 '
b10000000000000 %
b10000000000000 &
#3000
b1110 !
b1110 '
b100000000000000 %
b100000000000000 &
#3200
b1111 !
b1111 '
b1000000000000000 %
b1000000000000000 &
#3400
b1 *
b1 (
b1000000000000001 %
b1000000000000001 &
#3600
b1000 !
b1000 '
b100000001 %
b100000001 &
#3800
b1 "
b1 +
b1 #
b1 )
b11 *
b11 (
b1 !
b1 '
b11 %
b11 &
#4000
b0 "
b0 +
b0 #
b0 )
b0 *
b0 (
b0 !
b0 '
b0 %
b0 &
